op_code/__init__.py
op_code/ascii.py
op_code/binary.py
op_code/hexal.py
op_code/octal.py
op_code-0.0.1.dist-info/LICENSE.txt
op_code-0.0.1.dist-info/METADATA
op_code-0.0.1.dist-info/WHEEL
op_code-0.0.1.dist-info/top_level.txt
op_code-0.0.1.dist-info/RECORD
