Metadata-Version: 2.1
Name: op-code
Version: 0.0.1
Summary: Phoxett OP codec library for scientific solutions
Home-page: https://phoxett.github.io/op-code/
Author: Phoxett
Author-email: phoxett@gmail.com
Maintainer: Phoxett
Maintainer-email: phoxett@gmail.com
License: UNKNOWN
Platform: UNKNOWN
